never_sleep/__init__.py
never_sleep/__main__.py
never_sleep/cli.py
never_sleep-0.0.1.dist-info/LICENSE
never_sleep-0.0.1.dist-info/METADATA
never_sleep-0.0.1.dist-info/WHEEL
never_sleep-0.0.1.dist-info/entry_points.txt
never_sleep-0.0.1.dist-info/top_level.txt
never_sleep-0.0.1.dist-info/RECORD
