Metadata-Version: 2.1
Name: never-sleep
Version: 0.0.1
Summary: Never let the windows system sleep
Author: Sukhbinder Singh
License: Apache-2.0
Project-URL: Homepage, https://github.com/sukhbinder/never-sleep
Project-URL: Changelog, https://github.com/sukhbinder/never-sleep/releases
Project-URL: Issues, https://github.com/sukhbinder/never-sleep/issues
Project-URL: CI, https://github.com/sukhbinder/never-sleep/actions
Classifier: License :: OSI Approved :: Apache Software License
Requires-Python: >=3.8
License-File: LICENSE
Requires-Dist: keyboard
Provides-Extra: test
Requires-Dist: pytest; extra == "test"
